odoo/addons/account_invoice_default_code_column/README.rst
odoo/addons/account_invoice_default_code_column/__init__.py
odoo/addons/account_invoice_default_code_column/__manifest__.py
odoo/addons/account_invoice_default_code_column/i18n/account_invoice_default_code_column.pot
odoo/addons/account_invoice_default_code_column/i18n/es.po
odoo/addons/account_invoice_default_code_column/i18n/fr.po
odoo/addons/account_invoice_default_code_column/i18n/hr.po
odoo/addons/account_invoice_default_code_column/i18n/it.po
odoo/addons/account_invoice_default_code_column/models/__init__.py
odoo/addons/account_invoice_default_code_column/models/account_move_line.py
odoo/addons/account_invoice_default_code_column/readme/CONTRIBUTORS.rst
odoo/addons/account_invoice_default_code_column/readme/DESCRIPTION.rst
odoo/addons/account_invoice_default_code_column/reports/report_account_invoice.xml
odoo/addons/account_invoice_default_code_column/static/description/1_without_module.png
odoo/addons/account_invoice_default_code_column/static/description/2_with_module.png
odoo/addons/account_invoice_default_code_column/static/description/icon.png
odoo/addons/account_invoice_default_code_column/static/description/index.html
odoo_addon_account_invoice_default_code_column-16.0.1.0.1.dist-info/METADATA
odoo_addon_account_invoice_default_code_column-16.0.1.0.1.dist-info/WHEEL
odoo_addon_account_invoice_default_code_column-16.0.1.0.1.dist-info/top_level.txt
odoo_addon_account_invoice_default_code_column-16.0.1.0.1.dist-info/RECORD
